data_ingestion_tool/__init__.py
data_ingestion_tool/box_export.py
data_ingestion_tool/box_ingest.py
data_ingestion_tool-1.2.3.dist-info/METADATA
data_ingestion_tool-1.2.3.dist-info/WHEEL
data_ingestion_tool-1.2.3.dist-info/top_level.txt
data_ingestion_tool-1.2.3.dist-info/RECORD
