Metadata-Version: 2.1
Name: data-ingestion-tool
Version: 1.2.3
Summary: A toolset for ingesting data from Box into Delta tables, and exporting data to Box.
Author: Bug Hunter
Author-email: sayhi@thekingof.cool
Requires-Python: >=3.6
Requires-Dist: boxsdk
Requires-Dist: pandas
Requires-Dist: cerberus
Requires-Dist: cerberus-python-client
Requires-Dist: openpyxl
Requires-Dist: pyspark
Requires-Dist: delta-spark
